MANIFEST.in
README.md
setup.py
nesoi/__init__.py
nesoi/keystore.py
nesoi/rest.py
nesoi/service.py
nesoi.egg-info/PKG-INFO
nesoi.egg-info/SOURCES.txt
nesoi.egg-info/dependency_links.txt
nesoi.egg-info/top_level.txt
twisted/plugins/nesoi_plugin.py