Metadata-Version: 1.0
Name: nesoi
Version: 0.0.1
Summary: a coordination and configuration manager
Home-page: http://github.com/jrydberg/nesoi
Author: Johan Rydberg
Author-email: johan.rydberg@gmail.com
License: UNKNOWN
Platform: UNKNOWN
